pysympla/__init__.py
pysympla/event.py
pysympla/sympla.py
pysympla-0.0.6.dist-info/DESCRIPTION.rst
pysympla-0.0.6.dist-info/METADATA
pysympla-0.0.6.dist-info/RECORD
pysympla-0.0.6.dist-info/WHEEL
pysympla-0.0.6.dist-info/metadata.json
pysympla-0.0.6.dist-info/top_level.txt
